iceberg/__init__.py
iceberg/geometry.py
iceberg/utils.py
iceberg/animation/__init__.py
iceberg/animation/animatable.py
iceberg/animation/ease.py
iceberg/animation/scene.py
iceberg/animation/tween.py
iceberg/arrows/__init__.py
iceberg/core/__init__.py
iceberg/core/drawable.py
iceberg/core/properties.py
iceberg/core/renderer.py
iceberg/primitives/__init__.py
iceberg/primitives/filters.py
iceberg/primitives/image.py
iceberg/primitives/latex.py
iceberg/primitives/layout.py
iceberg/primitives/plotting.py
iceberg/primitives/shapes.py
iceberg/primitives/svg.py
iceberg/primitives/text.py
iceberg/primitives/typst.py
iceberg/trees/__init__.py
iceberg/trees/tree_layout.py
tests/__init__.py
tests/scene_tester.py
tests/test_animations.py
tests/test_blank.py
tests/test_connect.py
tests/test_filters.py
tests/test_neural_net.py
tests/test_paths.py
tests/test_quickstart.py
iceberg_dsl-0.1.2.dist-info/LICENSE
iceberg_dsl-0.1.2.dist-info/METADATA
iceberg_dsl-0.1.2.dist-info/WHEEL
iceberg_dsl-0.1.2.dist-info/top_level.txt
iceberg_dsl-0.1.2.dist-info/RECORD
