Metadata-Version: 2.1
Name: iceberg-dsl
Version: 0.1.2
Summary: A compositional diagramming tool for Python.
Home-page: https://github.com/revalo/iceberg
Author: Shreyas Kapur
Author-email: srkp@berkeley.edu
Maintainer: Shreyas Kapur
Maintainer-email: srkp@berkeley.edu
License: MIT
Project-URL: Documentation, https://github.com/revalo/iceberg/README.md
Project-URL: Code, https://github.com/revalo/iceberg
Project-URL: Issue tracker, https://github.com/revalo/iceberg/issues
Classifier: Development Status :: 3 - Alpha
Classifier: Environment :: Web Environment
Classifier: Intended Audience :: Developers
Classifier: License :: OSI Approved :: MIT License
Classifier: Operating System :: OS Independent
Classifier: Programming Language :: Python
Classifier: Topic :: Internet :: WWW/HTTP :: Dynamic Content
Classifier: Topic :: Internet :: WWW/HTTP :: WSGI
Classifier: Topic :: Internet :: WWW/HTTP :: WSGI :: Application
Classifier: Topic :: Software Development :: Libraries :: Application Frameworks
Requires-Python: >=3.10
License-File: LICENSE
Requires-Dist: absl-py >=1.0.0
Requires-Dist: glfw ==2.5.1
Requires-Dist: numpy >=1.21.0
Requires-Dist: skia-python ==87.5
Requires-Dist: tqdm >=4.62.3
Requires-Dist: av >=11.0.0
Requires-Dist: Pillow >=10.1.0
Requires-Dist: typing-extensions
Requires-Dist: lxml >=5.1.0
